pydc_control/__init__.py
pydc_control/cli.py
pydc_control/commands.py
pydc_control/config.py
pydc_control/data.py
pydc_control/docker_compose_utils.py
pydc_control/docker_utils.py
pydc_control/exceptions.py
pydc_control/log.py
pydc_control-2.96.dist-info/WHEEL
pydc_control-2.96.dist-info/METADATA
pydc_control-2.96.dist-info/RECORD
