Metadata-Version: 2.3
Name: pydc-control
Version: 2.96
Summary: Used to control multiple docker compose projects in a coordinated way.
Author: Adobe
Author-email: Adobe <noreply@adobe.com>
License: MIT
Classifier: Development Status :: 5 - Production/Stable
Classifier: License :: OSI Approved :: MIT License
Classifier: Operating System :: OS Independent
Classifier: Programming Language :: Python
Classifier: Programming Language :: Python :: 3
Classifier: Programming Language :: Python :: 3.8
Classifier: Programming Language :: Python :: 3.9
Classifier: Programming Language :: Python :: 3.10
Classifier: Programming Language :: Python :: 3.11
Requires-Dist: jinja2>=2.7.2
Requires-Dist: pyyaml>=5.1.2
Requires-Dist: requests
Requires-Dist: pre-commit>=2
Requires-Python: >=3.9
Project-URL: Homepage, https://github.com/adobe/pydc-control
Project-URL: Repository, https://github.com/adobe/pydc-control
